odoo/addons/sale_commission_queued/README.rst
odoo/addons/sale_commission_queued/__init__.py
odoo/addons/sale_commission_queued/__manifest__.py
odoo/addons/sale_commission_queued/i18n/es.po
odoo/addons/sale_commission_queued/i18n/it.po
odoo/addons/sale_commission_queued/i18n/sale_commission_queued.pot
odoo/addons/sale_commission_queued/readme/CONFIGURE.rst
odoo/addons/sale_commission_queued/readme/CONTRIBUTORS.rst
odoo/addons/sale_commission_queued/readme/DESCRIPTION.rst
odoo/addons/sale_commission_queued/readme/ROADMAP.rst
odoo/addons/sale_commission_queued/readme/USAGE.rst
odoo/addons/sale_commission_queued/static/description/icon.png
odoo/addons/sale_commission_queued/static/description/index.html
odoo/addons/sale_commission_queued/wizard/__init__.py
odoo/addons/sale_commission_queued/wizard/wizard_invoice.py
odoo/addons/sale_commission_queued/wizard/wizard_invoice.xml
odoo/addons/sale_commission_queued/wizard/wizard_settle.py
odoo/addons/sale_commission_queued/wizard/wizard_settle.xml
odoo14_addon_sale_commission_queued-14.0.1.1.1.dist-info/METADATA
odoo14_addon_sale_commission_queued-14.0.1.1.1.dist-info/WHEEL
odoo14_addon_sale_commission_queued-14.0.1.1.1.dist-info/top_level.txt
odoo14_addon_sale_commission_queued-14.0.1.1.1.dist-info/RECORD
