Metadata-Version: 2.1
Name: odoo14-addon-sale_commission_queued
Version: 14.0.1.1.1
Summary: Sales commissions queued
Home-page: https://github.com/OCA/commission
Author: Ilyas, Ooops404,Odoo Community Association (OCA)
Author-email: support@odoo-community.org
License: AGPL-3
Classifier: Programming Language :: Python
Classifier: Framework :: Odoo
Classifier: Framework :: Odoo :: 14.0
Classifier: License :: OSI Approved :: GNU Affero General Public License v3
Requires-Python: >=3.6
Requires-Dist: odoo14-addon-queue-job
Requires-Dist: odoo14-addon-sale-commission
Requires-Dist: odoo<14.1dev,>=14.0a
